{
  "scope": null,
  "attribute": 20,
  "displaySequence": 200,
  "label": "Message When No Data Found",
  "type": "Text",
  "required": "Yes",
  "common": "Yes",
  "showInWizard": "Yes",
  "defaultValue": "No data found.",
  "displayWidth": null,
  "maximumLength": null,
  "unit": null,
  "minimumColumns": null,
  "maximumColumns": null,
  "dataTypes": null,
  "parentAttributeId": null,
  "lovType": null,
  "lovComponentTypeId": null,
  "onDeleteBehavior": null,
  "setTextCase": null,
  "lovNullText": null,
  "userInterface": null,
  "supportedComponentTypes": null,
  "translatable": "Yes",
  "dependingOn": null,
  "alwaysEvaluate": null,
  "conditionType": null,
  "expression": null,
  "includeColumnsInItemsPicker": "Component",
  "examples": null,
  "helpText": "<p>Enter the message to be displayed when no data is found.</p>",
  "comment": null
}